[
  {
    "name": "CITY OF GRAND PRAIRIE LANDFILL",
    "type": "landfill",
    "address": "1102 MACARTHUR BLVD GRAND PRAIRIE TX 75050",
    "lat": 32.77,
    "lng": -96.95,
    "website": null,
    "source": null,
    "facility_id": "f_36b0f9b15da5"
  },
  {
    "name": "CITY OF GRAND PRAIRIE LF GAS TO ENERGY FACILITY",
    "type": "landfill",
    "address": "1102 MACARTHUR BLVD GRAND PRAIRIE TX 75050",
    "lat": 32.77,
    "lng": -96.95,
    "website": null,
    "source": null,
    "facility_id": "f_fa73f0f8a3b5"
  }
]