[
  {
    "name": "PRO STAR WASTE",
    "type": "landfill",
    "address": "7118 US HIGHWAY 59 S GOODRICH TX 77335",
    "lat": 30.49,
    "lng": -94.94,
    "website": null,
    "facility_id": "f_0e4a5dec6f65",
    "source": "tceq",
    "source_url": null,
    "osm_url": null
  },
  {
    "name": "PRO STAR WASTE",
    "type": "landfill",
    "address": "7118 US HIGHWAY 59 S GOODRICH TX 77335",
    "lat": 30.49,
    "lng": -94.94,
    "website": null,
    "facility_id": "f_7c00ff24255f",
    "source": "tceq",
    "source_url": null,
    "osm_url": null
  }
]